pAudio/__init__.py
pAudio/paplay.py
pAudio/parecord.py
paudio-0.3.0.dist-info/LICENSE
paudio-0.3.0.dist-info/METADATA
paudio-0.3.0.dist-info/WHEEL
paudio-0.3.0.dist-info/top_level.txt
paudio-0.3.0.dist-info/RECORD
